optilog.cpython-310-x86_64-linux-gnu.so
optilog.libs/libbz2-a273e504.so.1.0.6
optilog/py.typed
optilog/__init__.pyi
optilog/pycard.cpython-310-x86_64-linux-gnu.so
optilog/blackbox/satex.pyi
optilog/blackbox/enforcer.pyi
optilog/blackbox/__init__.pyi
optilog/blackbox/bb.pyi
optilog/applications/lsu.pyi
optilog/applications/__init__.pyi
optilog/applications/linear.pyi
optilog/formulas/wcnf.pyi
optilog/formulas/cnf.pyi
optilog/formulas/absformula.pyi
optilog/formulas/qcnf.pyi
optilog/formulas/__init__.pyi
optilog/formulas/loaders/wrapper.pyi
optilog/formulas/loaders/__init__.pyi
optilog/formulas/loaders/loaders.pyi
optilog/formulas/visualization/visualization.pyi
optilog/formulas/visualization/__init__.pyi
optilog/formulas/preprocessors/preprocessors.pyi
optilog/formulas/preprocessors/__init__.pyi
optilog/encoders/__init__.pyi
optilog/encoders/gadgets/__init__.pyi
optilog/encoders/pb/incremental_encoder.pyi
optilog/encoders/pb/encoder.pyi
optilog/encoders/pb/__init__.pyi
optilog/encoders/pb/extern/card.pyi
optilog/encoders/pb/extern/formula.pyi
optilog/encoders/pb/extern/_fileio.pyi
optilog/encoders/pb/extern/_utils.pyi
optilog/encoders/pb/extern/__init__.pyi
optilog/tuning/basis.pyi
optilog/tuning/__init__.pyi
optilog/tuning/configurators/smac.pyi
optilog/tuning/configurators/abstract_configurator.pyi
optilog/tuning/configurators/entrypoint.pyi
optilog/tuning/configurators/__init__.pyi
optilog/tuning/configurators/gga.pyi
optilog/tuning/configurators/configurator_wrapper.pyi
optilog/tuning/configurators/templates/wrapper_template.sh
optilog/tuning/configurators/utils/smac.pyi
optilog/tuning/configurators/utils/generic.pyi
optilog/tuning/configurators/utils/__init__.pyi
optilog/tuning/configurators/utils/gga.pyi
optilog/tuning/pbencoder/opb_parser.pyi
optilog/tuning/pbencoder/pycstr_encoder_transformer.pyi
optilog/tuning/pbencoder/pbencoder_transformer.pyi
optilog/tuning/pbencoder/__init__.pyi
optilog-0.6.0.dist-info/RECORD
optilog-0.6.0.dist-info/LICENSE
optilog-0.6.0.dist-info/METADATA
optilog-0.6.0.dist-info/entry_points.txt
optilog-0.6.0.dist-info/WHEEL
optilog-0.6.0.dist-info/top_level.txt
