Metadata-Version: 2.1
Name: optilog
Version: 0.6.0
Author: Logic and Optimization Group
License: Logic Optimization Group Academic License Agreement
Project-URL: Homepage, https://ulog.udl.cat/static/doc/optilog/html/index.html
Project-URL: Documentation, https://ulog.udl.cat/static/doc/optilog/html/index.html
Project-URL: Changelog, https://ulog.udl.cat/static/doc/optilog/html/optilog/changelog.html
Project-URL: Logic and Optimization Group, https://ulog.udl.cat/
Keywords: sat,maxsat,constraint,solver,problem
Platform: Linux
Classifier: Development Status :: 4 - Beta
Classifier: Intended Audience :: Developers
Classifier: Intended Audience :: Science/Research
Classifier: Natural Language :: English
Classifier: Programming Language :: Python :: 3
Classifier: Operating System :: POSIX :: Linux
Classifier: Topic :: Scientific/Engineering
Classifier: Topic :: Scientific/Engineering :: Artificial Intelligence
Requires-Python: >=3.8
License-File: LICENSE
Requires-Dist: pypblib >=0.0.4
Requires-Dist: pandas >=1.1.5
Requires-Dist: tabulate >=0.8.9
Requires-Dist: sly ==0.4
Requires-Dist: appdirs
Requires-Dist: termcolor
